PDFScraper/__init__.py
PDFScraper/__main__.py
PDFScraper/cli.py
PDFScraper/core.py
PDFScraper/dataStructure.py
PDFScraper/outputGenerator.py
PDFScraper-1.1.9.dist-info/LICENSE
PDFScraper-1.1.9.dist-info/METADATA
PDFScraper-1.1.9.dist-info/WHEEL
PDFScraper-1.1.9.dist-info/top_level.txt
PDFScraper-1.1.9.dist-info/RECORD
