Metadata-Version: 2.1
Name: PDFScraper
Version: 1.1.9
Summary: PDF text and table search
Author: Erik Kastelec, email = erikkastelec@gmail.com
Classifier: Programming Language :: Python :: 3
Classifier: License :: OSI Approved :: MIT License
Classifier: Operating System :: OS Independent
Requires-Python: >=3.9
License-File: LICENSE
Requires-Dist: camelot-py
Requires-Dist: cffi
Requires-Dist: chardet
Requires-Dist: charset-normalizer
Requires-Dist: click
Requires-Dist: cryptography
Requires-Dist: distro
Requires-Dist: et-xmlfile
Requires-Dist: fuzzywuzzy
Requires-Dist: ghostscript
Requires-Dist: imageio
Requires-Dist: iso639
Requires-Dist: langdetect
Requires-Dist: lazy-loader
Requires-Dist: Levenshtein
Requires-Dist: networkx
Requires-Dist: numpy
Requires-Dist: opencv-python
Requires-Dist: openpyxl
Requires-Dist: packaging
Requires-Dist: pandas
Requires-Dist: pdf2image
Requires-Dist: pdfminer.six
Requires-Dist: pillow
Requires-Dist: psutil
Requires-Dist: pycparser
Requires-Dist: pypdf
Requires-Dist: pytesseract
Requires-Dist: python-dateutil
Requires-Dist: python-Levenshtein
Requires-Dist: pytz
Requires-Dist: rapidfuzz
Requires-Dist: scikit-image
Requires-Dist: scipy
Requires-Dist: six
Requires-Dist: tabula-py
Requires-Dist: tabulate
Requires-Dist: tifffile
Requires-Dist: typing-extensions
Requires-Dist: tzdata
Requires-Dist: wand
Requires-Dist: yattag
